QuantumTomography/TomoClass.py
QuantumTomography/TomoClassHelpers.py
QuantumTomography/TomoDisplay.py
QuantumTomography/TomoDisplayHelpers.py
QuantumTomography/TomoFunctions.py
QuantumTomography/TomoFunctionsHelpers.py
QuantumTomography/Utilities.py
QuantumTomography/__init__.py
QuantumTomography/cli.py
quantum_tomography-1.2.0.dist-info/licenses/LICENSE
quantum_tomography-1.2.0.dist-info/METADATA
quantum_tomography-1.2.0.dist-info/WHEEL
quantum_tomography-1.2.0.dist-info/entry_points.txt
quantum_tomography-1.2.0.dist-info/top_level.txt
quantum_tomography-1.2.0.dist-info/RECORD
