Metadata-Version: 2.4
Name: Quantum-Tomography
Version: 1.2.0
Summary: A comprehensive quantum tomography library.
Author-email: Benjamin Nussbaum <bn9@illinois.edu>, Timur Javid <tjavid2@illinois.edu>
Maintainer-email: Benjamin Nussbaum <bn9@illinois.edu>, Timur Javid <tjavid2@illinois.edu>
License: MIT
Project-URL: Homepage, https://quantumtomo.web.illinois.edu/
Project-URL: Documentation, https://quantumtomo.web.illinois.edu/Doc
Project-URL: Repository, https://github.com/KwiatLab/quantum-tomography
Project-URL: Video Tutorial, https://www.youtube.com/watch?v=I-214P0LOfQ&list=PLJLHMKtk5Pqy9w9aCuyowUF1p7pl2JCI9&index=3
Keywords: quantum tomography,state tomography,process tomography,quantum information
Classifier: Development Status :: 5 - Production/Stable
Classifier: Intended Audience :: Science/Research
Classifier: License :: OSI Approved :: MIT License
Classifier: Programming Language :: Python :: 3.11
Classifier: Programming Language :: Python :: 3.12
Classifier: Programming Language :: Python :: 3.13
Classifier: Programming Language :: Python :: 3.14
Classifier: Topic :: Scientific/Engineering :: Physics
Requires-Python: >=3.11
License-File: LICENSE
Requires-Dist: numpy>=2.1.3
Requires-Dist: scipy>=1.14.1
Requires-Dist: matplotlib
Requires-Dist: tomli-w>=1.2.0
Dynamic: license-file
